[
  {
    "番号": 1,
    "カテゴリ": "暮らし",
    "テーマ": "週末のモーニングルーティン",
    "フォーマット": "リール",
    "フック（冒頭文）": "休日の朝、丁寧に過ごす",
    "キャプション案": "休日の朝、丁寧に過ごす\n\n────────────────────\n[本文をここに記載]\n────────────────────\n\n#暮らし #一人暮らし #丁寧な暮らし #シンプルライフ #暮らしを楽しむ #日々の暮らし #ルームツアー #部屋作り #日常 #vlog #ライフスタイル #大学生",
    "推奨ハッシュタグ": [
      "#暮らし",
      "#一人暮らし",
      "#丁寧な暮らし",
      "#シンプルライフ",
      "#暮らしを楽しむ",
      "#日々の暮らし",
      "#ルームツアー",
      "#部屋作り",
      "#日常",
      "#vlog",
      "#ライフスタイル",
      "#大学生"
    ],
    "推奨投稿時間": "金曜日 0:00",
    "ポイント": "生活感のあるナチュラルな雰囲気。BGMは落ち着いた曲。整理整頓されたビジュアルが伸びやすい / 冒頭1秒でフック。テンポよく編集。トレンド音源を活用"
  },
  {
    "番号": 2,
    "カテゴリ": "自分磨き",
    "テーマ": "おすすめ本紹介",
    "フォーマット": "カルーセル",
    "フック（冒頭文）": "人生変わった本5冊",
    "キャプション案": "人生変わった本5冊\n\n────────────────────\n[本文をここに記載]\n────────────────────\n\n#自分磨き #自分磨き男子 #モーニングルーティン #朝活 #習慣化 #読書 #成長記録 #QOL向上 #日常 #vlog #ライフスタイル #大学生",
    "推奨ハッシュタグ": [
      "#自分磨き",
      "#自分磨き男子",
      "#モーニングルーティン",
      "#朝活",
      "#習慣化",
      "#読書",
      "#成長記録",
      "#QOL向上",
      "#日常",
      "#vlog",
      "#ライフスタイル",
      "#大学生"
    ],
    "推奨投稿時間": "土曜日 0:00",
    "ポイント": "共感を呼ぶ「変わりたい」というストーリー性。具体的なアクションを提示 / 1枚目が命。文字は大きく読みやすく。最後にCTA（保存・フォロー促進）"
  },
  {
    "番号": 3,
    "カテゴリ": "大学生活",
    "テーマ": "大学生の1日",
    "フォーマット": "リール",
    "フック（冒頭文）": "授業・バイト・筋トレを両立する1日",
    "キャプション案": "授業・バイト・筋トレを両立する1日\n\n────────────────────\n[本文をここに記載]\n────────────────────\n\n#大学生 #大学生の日常 #大学生活 #キャンパスライフ #大学生の暮らし #大学生vlog #日常 #vlog #ライフスタイル",
    "推奨ハッシュタグ": [
      "#大学生",
      "#大学生の日常",
      "#大学生活",
      "#キャンパスライフ",
      "#大学生の暮らし",
      "#大学生vlog",
      "#日常",
      "#vlog",
      "#ライフスタイル"
    ],
    "推奨投稿時間": "木曜日 0:00",
    "ポイント": "リアル感が大事。同世代の「あるある」共感を狙う / 冒頭1秒でフック。テンポよく編集。トレンド音源を活用"
  },
  {
    "番号": 4,
    "カテゴリ": "自分磨き",
    "テーマ": "習慣化のコツ",
    "フォーマット": "カルーセル",
    "フック（冒頭文）": "三日坊主だった僕が習慣化できた方法",
    "キャプション案": "三日坊主だった僕が習慣化できた方法\n\n────────────────────\n[本文をここに記載]\n────────────────────\n\n#自分磨き #自分磨き男子 #モーニングルーティン #朝活 #習慣化 #読書 #成長記録 #QOL向上 #日常 #vlog #ライフスタイル #大学生",
    "推奨ハッシュタグ": [
      "#自分磨き",
      "#自分磨き男子",
      "#モーニングルーティン",
      "#朝活",
      "#習慣化",
      "#読書",
      "#成長記録",
      "#QOL向上",
      "#日常",
      "#vlog",
      "#ライフスタイル",
      "#大学生"
    ],
    "推奨投稿時間": "金曜日 12:00",
    "ポイント": "共感を呼ぶ「変わりたい」というストーリー性。具体的なアクションを提示 / 1枚目が命。文字は大きく読みやすく。最後にCTA（保存・フォロー促進）"
  },
  {
    "番号": 5,
    "カテゴリ": "自分磨き",
    "テーマ": "目標設定",
    "フォーマット": "カルーセル",
    "フック（冒頭文）": "今年やりたいこと100リスト",
    "キャプション案": "今年やりたいこと100リスト\n\n────────────────────\n[本文をここに記載]\n────────────────────\n\n#自分磨き #自分磨き男子 #モーニングルーティン #朝活 #習慣化 #読書 #成長記録 #QOL向上 #日常 #vlog #ライフスタイル #大学生",
    "推奨ハッシュタグ": [
      "#自分磨き",
      "#自分磨き男子",
      "#モーニングルーティン",
      "#朝活",
      "#習慣化",
      "#読書",
      "#成長記録",
      "#QOL向上",
      "#日常",
      "#vlog",
      "#ライフスタイル",
      "#大学生"
    ],
    "推奨投稿時間": "土曜日 1:00",
    "ポイント": "共感を呼ぶ「変わりたい」というストーリー性。具体的なアクションを提示 / 1枚目が命。文字は大きく読みやすく。最後にCTA（保存・フォロー促進）"
  },
  {
    "番号": 6,
    "カテゴリ": "自分磨き",
    "テーマ": "朝活ルーティン",
    "フォーマット": "リール",
    "フック（冒頭文）": "5時起きを1ヶ月続けた結果",
    "キャプション案": "5時起きを1ヶ月続けた結果\n\n────────────────────\n[本文をここに記載]\n────────────────────\n\n#自分磨き #自分磨き男子 #モーニングルーティン #朝活 #習慣化 #読書 #成長記録 #QOL向上 #日常 #vlog #ライフスタイル #大学生",
    "推奨ハッシュタグ": [
      "#自分磨き",
      "#自分磨き男子",
      "#モーニングルーティン",
      "#朝活",
      "#習慣化",
      "#読書",
      "#成長記録",
      "#QOL向上",
      "#日常",
      "#vlog",
      "#ライフスタイル",
      "#大学生"
    ],
    "推奨投稿時間": "木曜日 1:00",
    "ポイント": "共感を呼ぶ「変わりたい」というストーリー性。具体的なアクションを提示 / 冒頭1秒でフック。テンポよく編集。トレンド音源を活用"
  },
  {
    "番号": 7,
    "カテゴリ": "自分磨き",
    "テーマ": "1日のスケジュール",
    "フォーマット": "カルーセル/リール",
    "フック（冒頭文）": "大学生のリアルな1日",
    "キャプション案": "大学生のリアルな1日\n\n────────────────────\n[本文をここに記載]\n────────────────────\n\n#自分磨き #自分磨き男子 #モーニングルーティン #朝活 #習慣化 #読書 #成長記録 #QOL向上 #日常 #vlog #ライフスタイル #大学生",
    "推奨ハッシュタグ": [
      "#自分磨き",
      "#自分磨き男子",
      "#モーニングルーティン",
      "#朝活",
      "#習慣化",
      "#読書",
      "#成長記録",
      "#QOL向上",
      "#日常",
      "#vlog",
      "#ライフスタイル",
      "#大学生"
    ],
    "推奨投稿時間": "金曜日 12:00",
    "ポイント": "共感を呼ぶ「変わりたい」というストーリー性。具体的なアクションを提示 / 冒頭1秒でフック。テンポよく編集。トレンド音源を活用"
  },
  {
    "番号": 8,
    "カテゴリ": "暮らし",
    "テーマ": "ナイトルーティン",
    "フォーマット": "リール",
    "フック（冒頭文）": "次の日を最高にする夜の過ごし方",
    "キャプション案": "次の日を最高にする夜の過ごし方\n\n────────────────────\n[本文をここに記載]\n────────────────────\n\n#暮らし #一人暮らし #丁寧な暮らし #シンプルライフ #暮らしを楽しむ #日々の暮らし #ルームツアー #部屋作り #日常 #vlog #ライフスタイル #大学生",
    "推奨ハッシュタグ": [
      "#暮らし",
      "#一人暮らし",
      "#丁寧な暮らし",
      "#シンプルライフ",
      "#暮らしを楽しむ",
      "#日々の暮らし",
      "#ルームツアー",
      "#部屋作り",
      "#日常",
      "#vlog",
      "#ライフスタイル",
      "#大学生"
    ],
    "推奨投稿時間": "土曜日 12:00",
    "ポイント": "生活感のあるナチュラルな雰囲気。BGMは落ち着いた曲。整理整頓されたビジュアルが伸びやすい / 冒頭1秒でフック。テンポよく編集。トレンド音源を活用"
  },
  {
    "番号": 9,
    "カテゴリ": "暮らし",
    "テーマ": "自炊レシピ紹介",
    "フォーマット": "カルーセル",
    "フック（冒頭文）": "一人暮らし男子の簡単ごはん",
    "キャプション案": "一人暮らし男子の簡単ごはん\n\n────────────────────\n[本文をここに記載]\n────────────────────\n\n#暮らし #一人暮らし #丁寧な暮らし #シンプルライフ #暮らしを楽しむ #日々の暮らし #ルームツアー #部屋作り #日常 #vlog #ライフスタイル #大学生",
    "推奨ハッシュタグ": [
      "#暮らし",
      "#一人暮らし",
      "#丁寧な暮らし",
      "#シンプルライフ",
      "#暮らしを楽しむ",
      "#日々の暮らし",
      "#ルームツアー",
      "#部屋作り",
      "#日常",
      "#vlog",
      "#ライフスタイル",
      "#大学生"
    ],
    "推奨投稿時間": "木曜日 12:00",
    "ポイント": "生活感のあるナチュラルな雰囲気。BGMは落ち着いた曲。整理整頓されたビジュアルが伸びやすい / 1枚目が命。文字は大きく読みやすく。最後にCTA（保存・フォロー促進）"
  },
  {
    "番号": 10,
    "カテゴリ": "暮らし",
    "テーマ": "買ってよかったもの紹介",
    "フォーマット": "カルーセル/リール",
    "フック（冒頭文）": "QOL爆上がりアイテム5選",
    "キャプション案": "QOL爆上がりアイテム5選\n\n────────────────────\n[本文をここに記載]\n────────────────────\n\n#暮らし #一人暮らし #丁寧な暮らし #シンプルライフ #暮らしを楽しむ #日々の暮らし #ルームツアー #部屋作り #日常 #vlog #ライフスタイル #大学生",
    "推奨ハッシュタグ": [
      "#暮らし",
      "#一人暮らし",
      "#丁寧な暮らし",
      "#シンプルライフ",
      "#暮らしを楽しむ",
      "#日々の暮らし",
      "#ルームツアー",
      "#部屋作り",
      "#日常",
      "#vlog",
      "#ライフスタイル",
      "#大学生"
    ],
    "推奨投稿時間": "金曜日 12:00",
    "ポイント": "生活感のあるナチュラルな雰囲気。BGMは落ち着いた曲。整理整頓されたビジュアルが伸びやすい / 冒頭1秒でフック。テンポよく編集。トレンド音源を活用"
  }
]